quizwiz/__init__.py
quizwiz/authenticator/__init__.py
quizwiz/authenticator/__main__.py
quizwiz/authenticator/auth_app.py
quizwiz/authenticator/auth_config.py
quizwiz/backend/__init__.py
quizwiz/backend/config.py
quizwiz/backend/file_manager.py
quizwiz/backend/log_manager.py
quizwiz/backend/main.py
quizwiz/backend/util.py
quizwiz/frontend/__init__.py
quizwiz/frontend/answer.py
quizwiz/frontend/app.py
quizwiz/frontend/config.py
quizwiz/frontend/constant.py
quizwiz/frontend/hello.py
quizwiz/frontend/intro.py
quizwiz/frontend/pages.py
quizwiz/frontend/problem.py
quizwiz/frontend/problem_step.py
quizwiz/frontend/review.py
quizwiz/frontend/i18n/__init__.py
quizwiz/frontend/i18n/i18n.py
quizwiz/frontend/utils/__init__.py
quizwiz/frontend/utils/admin.py
quizwiz/frontend/utils/common.py
quizwiz/frontend/utils/graph_elem.py
quizwiz/frontend/utils/http.py
quizwiz/frontend/utils/image_elem.py
quizwiz/frontend/utils/log.py
quizwiz/frontend/utils/page_manager.py
quizwiz/frontend/utils/text_elem.py
quizwiz-1.0.0.dist-info/LICENSE
quizwiz-1.0.0.dist-info/METADATA
quizwiz-1.0.0.dist-info/WHEEL
quizwiz-1.0.0.dist-info/top_level.txt
quizwiz-1.0.0.dist-info/RECORD
