Metadata-Version: 2.1
Name: quizwiz
Version: 1.0.0
Summary: A quiz system for developers
Home-page: UNKNOWN
Author: byoungwoo.yoon
Author-email: byoungwoo.yoon@samsung.com
License: UNKNOWN
Platform: UNKNOWN
Classifier: Programming Language :: Python :: 3
Classifier: License :: OSI Approved :: MIT License
Classifier: Operating System :: OS Independent
Requires-Python: >=3.9
License-File: LICENSE
Requires-Dist: Faker==30.8.2
Requires-Dist: GitPython==3.1.43
Requires-Dist: Jinja2==3.1.4
Requires-Dist: Markdown==3.7
Requires-Dist: MarkupSafe==3.0.2
Requires-Dist: PyJWT==2.9.0
Requires-Dist: PyYAML==6.0.2
Requires-Dist: Pygments==2.18.0
Requires-Dist: SQLAlchemy==2.0.36
Requires-Dist: altair==5.4.1
Requires-Dist: annotated-types==0.7.0
Requires-Dist: anyio==4.6.2.post1
Requires-Dist: anywidget==0.9.13
Requires-Dist: appdirs==1.4.4
Requires-Dist: arrow==1.3.0
Requires-Dist: astor==0.8.1
Requires-Dist: astroid==3.3.5
Requires-Dist: asttokens==2.4.1
Requires-Dist: attrs==24.2.0
Requires-Dist: backoff==2.2.1
Requires-Dist: beautifulsoup4==4.12.3
Requires-Dist: black==24.10.0
Requires-Dist: blinker==1.9.0
Requires-Dist: cachetools==5.5.0
Requires-Dist: certifi==2024.8.30
Requires-Dist: cffi==1.17.1
Requires-Dist: charset-normalizer==3.4.0
Requires-Dist: click==8.1.7
Requires-Dist: colorama==0.4.6
Requires-Dist: comm==0.2.2
Requires-Dist: contourpy==1.3.0
Requires-Dist: cryptography==43.0.3
Requires-Dist: cycler==0.12.1
Requires-Dist: dateutils==0.6.12
Requires-Dist: debugpy==1.8.11
Requires-Dist: decorator==5.1.1
Requires-Dist: dill==0.3.9
Requires-Dist: duckdb==1.1.3
Requires-Dist: entrypoints==0.4
Requires-Dist: executing==2.1.0
Requires-Dist: fastapi==0.115.4
Requires-Dist: favicon==0.7.0
Requires-Dist: fonttools==4.54.1
Requires-Dist: gitdb==4.0.11
Requires-Dist: greenlet==3.1.1
Requires-Dist: gw-dsl-parser==0.1.49.1
Requires-Dist: h11==0.14.0
Requires-Dist: htbuilder==0.6.2
Requires-Dist: httpcore==1.0.6
Requires-Dist: httpx==0.27.2
Requires-Dist: icecream==2.1.3
Requires-Dist: idna==3.10
Requires-Dist: importlib-resources==6.4.5
Requires-Dist: iniconfig==2.0.0
Requires-Dist: ipykernel==6.29.5
Requires-Dist: ipylab==1.0.0
Requires-Dist: ipython==8.29.0
Requires-Dist: ipywidgets==8.1.5
Requires-Dist: isort==5.13.2
Requires-Dist: jedi==0.19.2
Requires-Dist: jsonschema-specifications==2024.10.1
Requires-Dist: jsonschema==4.23.0
Requires-Dist: jupyter-client==8.6.3
Requires-Dist: jupyter-core==5.7.2
Requires-Dist: jupyterlab-widgets==3.0.13
Requires-Dist: kanaries-track==0.0.5
Requires-Dist: kiwisolver==1.4.7
Requires-Dist: lxml==5.3.0
Requires-Dist: markdown-it-py==3.0.0
Requires-Dist: markdownlit==0.0.7
Requires-Dist: matplotlib-inline==0.1.7
Requires-Dist: matplotlib==3.9.2
Requires-Dist: mccabe==0.7.0
Requires-Dist: mdurl==0.1.2
Requires-Dist: monotonic==1.6
Requires-Dist: more-itertools==10.5.0
Requires-Dist: mypy-extensions==1.0.0
Requires-Dist: narwhals==1.13.3
Requires-Dist: nest-asyncio==1.6.0
Requires-Dist: numpy==1.26.4
Requires-Dist: packaging==24.2
Requires-Dist: pandas==2.2.3
Requires-Dist: parso==0.8.4
Requires-Dist: pathspec==0.12.1
Requires-Dist: pexpect==4.9.0
Requires-Dist: pillow==11.0.0
Requires-Dist: platformdirs==4.3.6
Requires-Dist: plotly==5.24.1
Requires-Dist: pluggy==1.5.0
Requires-Dist: prometheus-client==0.21.0
Requires-Dist: prompt-toolkit==3.0.48
Requires-Dist: protobuf==5.28.3
Requires-Dist: psutil==6.1.0
Requires-Dist: psygnal==0.11.1
Requires-Dist: ptyprocess==0.7.0
Requires-Dist: pure-eval==0.2.3
Requires-Dist: pyarrow==18.0.0
Requires-Dist: pycparser==2.22
Requires-Dist: pydantic==2.9.2
Requires-Dist: pydantic-core==2.23.4
Requires-Dist: pydeck==0.9.1
Requires-Dist: pyfakefs==5.7.1
Requires-Dist: pygwalker==0.4.9.13
Requires-Dist: pylint==3.3.1
Requires-Dist: pymdown-extensions==10.12
Requires-Dist: pyparsing==3.2.0
Requires-Dist: pytest==8.3.3
Requires-Dist: python-dateutil==2.9.0.post0
Requires-Dist: python-dotenv==1.0.1
Requires-Dist: python-multipart==0.0.17
Requires-Dist: pytz==2024.2
Requires-Dist: pyzmq==26.2.0
Requires-Dist: quickjs==1.19.4
Requires-Dist: referencing==0.35.1
Requires-Dist: requests==2.32.3
Requires-Dist: rich==13.9.4
Requires-Dist: rpds-py==0.21.0
Requires-Dist: scipy==1.14.1
Requires-Dist: seaborn==0.13.2
Requires-Dist: segment-analytics-python==2.2.3
Requires-Dist: six==1.16.0
Requires-Dist: smmap==5.0.1
Requires-Dist: sniffio==1.3.1
Requires-Dist: soupsieve==2.6
Requires-Dist: sqlglot==25.30.0
Requires-Dist: st-annotated-text==4.0.1
Requires-Dist: st-theme==1.2.3
Requires-Dist: stack-data==0.6.3
Requires-Dist: starlette==0.41.2
Requires-Dist: streamlit-camera-input-live==0.2.0
Requires-Dist: streamlit-card==1.0.2
Requires-Dist: streamlit-cookies-controller==0.0.4
Requires-Dist: streamlit-embedcode==0.1.2
Requires-Dist: streamlit-extras==0.5.0
Requires-Dist: streamlit-faker==0.0.3
Requires-Dist: streamlit-image-coordinates==0.1.9
Requires-Dist: streamlit-keyup==0.2.4
Requires-Dist: streamlit-option-menu==0.4.0
Requires-Dist: streamlit-toggle-switch==1.0.2
Requires-Dist: streamlit-vertical-slider==2.5.5
Requires-Dist: streamlit==1.40.1
Requires-Dist: tabulate==0.9.0
Requires-Dist: tenacity==9.0.0
Requires-Dist: toml==0.10.2
Requires-Dist: tomlkit==0.13.2
Requires-Dist: tornado==6.4.1
Requires-Dist: traitlets==5.14.3
Requires-Dist: types-python-dateutil==2.9.0.20241003
Requires-Dist: typing-extensions==4.12.2
Requires-Dist: tzdata==2024.2
Requires-Dist: urllib3==2.2.3
Requires-Dist: uvicorn==0.32.0
Requires-Dist: validators==0.34.0
Requires-Dist: wasmtime==25.0.0
Requires-Dist: watchdog==6.0.0
Requires-Dist: wcwidth==0.2.13
Requires-Dist: widgetsnbextension==4.0.13
